CHANGES.md
MANIFEST.in
README.md
setup.py
./wrappers/__init__.py
./wrappers/_version.py
./wrappers/amber.py
./wrappers/grompp.py
./wrappers/lsdmap.py
./wrappers/mdrun.py
./wrappers/pack.py
./wrappers/pycoco.py
./wrappers/reweighting.py
./wrappers/script.py
./wrappers/selection.py
./wrappers/tools/__init__.py
./wrappers/tools/pack.py
extasy.wrappers.egg-info/PKG-INFO
extasy.wrappers.egg-info/SOURCES.txt
extasy.wrappers.egg-info/dependency_links.txt
extasy.wrappers.egg-info/namespace_packages.txt
extasy.wrappers.egg-info/not-zip-safe
extasy.wrappers.egg-info/top_level.txt