Metadata-Version: 1.1
Name: extasy.wrappers
Version: 0.0.6
Summary: EXTASY Project - Wrappers
Home-page: https://bitbucket.org/extasy-project/extasy-project
Author: The EXTASY Project
Author-email: UNKNOWN
License: BSD
Download-URL: https://bitbucket.org/extasy-project/wrappers/get/0.0.6.tar.gz
Platform: UNKNOWN
Classifier: Development Status :: 3 - Alpha
Classifier: Intended Audience :: Developers
Classifier: Environment :: Console
Classifier: License :: OSI Approved :: MIT License
Classifier: Programming Language :: Python
Classifier: Programming Language :: Python :: 2
Classifier: Programming Language :: Python :: 2.6
Classifier: Programming Language :: Python :: 2.7
Classifier: Topic :: Utilities
Classifier: Topic :: System :: Distributed Computing
Classifier: Operating System :: MacOS :: MacOS X
Classifier: Operating System :: POSIX
Classifier: Operating System :: Unix
